xdem/__init__.py
xdem/_typing.py
xdem/_version.py
xdem/ddem.py
xdem/dem.py
xdem/demcollection.py
xdem/examples.py
xdem/filters.py
xdem/fit.py
xdem/misc.py
xdem/spatialstats.py
xdem/terrain.py
xdem/vcrs.py
xdem/volume.py
xdem/coreg/__init__.py
xdem/coreg/affine.py
xdem/coreg/base.py
xdem/coreg/biascorr.py
xdem/coreg/blockwise.py
xdem/coreg/filters.py
xdem-0.1.5.dist-info/licenses/LICENSE
xdem-0.1.5.dist-info/METADATA
xdem-0.1.5.dist-info/WHEEL
xdem-0.1.5.dist-info/top_level.txt
xdem-0.1.5.dist-info/RECORD
