Metadata-Version: 2.4
Name: xdem
Version: 0.1.5
Summary: Analysis of digital elevation models (DEMs)
Home-page: https://github.com/GlacioHack/xdem
Download-URL: https://pypi.org/project/xdem/
Author: xDEM developers
License: Apache-2.0
Keywords: dem,elevation,geoutils,xarray
Platform: any
Classifier: Development Status :: 4 - Beta
Classifier: Intended Audience :: Developers
Classifier: Intended Audience :: Science/Research
Classifier: Natural Language :: English
Classifier: Operating System :: OS Independent
Classifier: Topic :: Scientific/Engineering :: GIS
Classifier: Topic :: Scientific/Engineering :: Image Processing
Classifier: Topic :: Scientific/Engineering :: Information Analysis
Classifier: Programming Language :: Python
Classifier: Programming Language :: Python :: 3.10
Classifier: Programming Language :: Python :: 3.11
Classifier: Programming Language :: Python :: 3.12
Classifier: Programming Language :: Python :: 3.13
Classifier: Programming Language :: Python :: 3
Classifier: Topic :: Software Development :: Libraries :: Python Modules
Classifier: Typing :: Typed
Requires-Python: <3.14,>=3.10
License-File: LICENSE
Requires-Dist: geopandas>=0.12.0
Requires-Dist: numba==0.*
Requires-Dist: numpy<3,>=1
Requires-Dist: matplotlib==3.*
Requires-Dist: pyproj<4,>=3.4
Requires-Dist: rasterio<2,>=1.3
Requires-Dist: scipy==1.*
Requires-Dist: tqdm
Requires-Dist: geoutils==0.1.17
Requires-Dist: affine
Requires-Dist: pandas
Requires-Dist: pyogrio
Requires-Dist: shapely
Requires-Dist: pip
Provides-Extra: opt
Requires-Dist: pytransform3d; extra == "opt"
Requires-Dist: scikit-learn; extra == "opt"
Requires-Dist: scikit-gstat; extra == "opt"
Requires-Dist: pyyaml; extra == "opt"
Provides-Extra: test
Requires-Dist: pytest; extra == "test"
Requires-Dist: pytest-xdist; extra == "test"
Requires-Dist: pre-commit; extra == "test"
Requires-Dist: flake8; extra == "test"
Requires-Dist: pylint; extra == "test"
Requires-Dist: scikit-learn; extra == "test"
Provides-Extra: doc
Requires-Dist: sphinx; extra == "doc"
Requires-Dist: sphinx-book-theme; extra == "doc"
Requires-Dist: sphinxcontrib-programoutput; extra == "doc"
Requires-Dist: sphinx-design; extra == "doc"
Requires-Dist: sphinx-autodoc-typehints; extra == "doc"
Requires-Dist: sphinx-gallery; extra == "doc"
Requires-Dist: autovizwidget; extra == "doc"
Requires-Dist: graphviz; extra == "doc"
Requires-Dist: myst-nb; extra == "doc"
Requires-Dist: numpydoc; extra == "doc"
Provides-Extra: dev
Requires-Dist: pytransform3d; extra == "dev"
Requires-Dist: scikit-learn; extra == "dev"
Requires-Dist: scikit-gstat; extra == "dev"
Requires-Dist: pyyaml; extra == "dev"
Requires-Dist: sphinx; extra == "dev"
Requires-Dist: sphinx-book-theme; extra == "dev"
Requires-Dist: sphinxcontrib-programoutput; extra == "dev"
Requires-Dist: sphinx-design; extra == "dev"
Requires-Dist: sphinx-autodoc-typehints; extra == "dev"
Requires-Dist: sphinx-gallery; extra == "dev"
Requires-Dist: autovizwidget; extra == "dev"
Requires-Dist: graphviz; extra == "dev"
Requires-Dist: myst-nb; extra == "dev"
Requires-Dist: numpydoc; extra == "dev"
Requires-Dist: pytest; extra == "dev"
Requires-Dist: pytest-xdist; extra == "dev"
Requires-Dist: pre-commit; extra == "dev"
Requires-Dist: flake8; extra == "dev"
Requires-Dist: pylint; extra == "dev"
Requires-Dist: scikit-learn; extra == "dev"
Provides-Extra: all
Requires-Dist: pytransform3d; extra == "all"
Requires-Dist: scikit-learn; extra == "all"
Requires-Dist: scikit-gstat; extra == "all"
Requires-Dist: pyyaml; extra == "all"
Requires-Dist: sphinx; extra == "all"
Requires-Dist: sphinx-book-theme; extra == "all"
Requires-Dist: sphinxcontrib-programoutput; extra == "all"
Requires-Dist: sphinx-design; extra == "all"
Requires-Dist: sphinx-autodoc-typehints; extra == "all"
Requires-Dist: sphinx-gallery; extra == "all"
Requires-Dist: autovizwidget; extra == "all"
Requires-Dist: graphviz; extra == "all"
Requires-Dist: myst-nb; extra == "all"
Requires-Dist: numpydoc; extra == "all"
Requires-Dist: pytest; extra == "all"
Requires-Dist: pytest-xdist; extra == "all"
Requires-Dist: pre-commit; extra == "all"
Requires-Dist: flake8; extra == "all"
Requires-Dist: pylint; extra == "all"
Requires-Dist: scikit-learn; extra == "all"
Dynamic: download-url
Dynamic: license-file
